abeiai/__init__.py
abeiai/v1.py
abeiai-1.0.0.dist-info/LICENSE
abeiai-1.0.0.dist-info/METADATA
abeiai-1.0.0.dist-info/WHEEL
abeiai-1.0.0.dist-info/top_level.txt
abeiai-1.0.0.dist-info/RECORD
