Metadata-Version: 2.1
Name: abeiai
Version: 1.0.0
Summary: 阿贝智能开放平台SDK
Home-page: https://github.com/spirits001/abeiai.git
Author: 代码厨子
Author-email: 15755153@qq.com
Classifier: Programming Language :: Python :: 3
Classifier: License :: OSI Approved :: MIT License
Classifier: Operating System :: OS Independent
Requires-Python: >=3
License-File: LICENSE
Requires-Dist: requests
